databricks_registry_webhooks/__init__.py
databricks_registry_webhooks/client.py
databricks_registry_webhooks/exceptions.py
databricks_registry_webhooks/version.py
databricks_registry_webhooks/entities/__init__.py
databricks_registry_webhooks/entities/_webhooks_base_object.py
databricks_registry_webhooks/entities/http_url_spec.py
databricks_registry_webhooks/entities/job_spec.py
databricks_registry_webhooks/entities/registry_webhook.py
databricks_registry_webhooks/entities/registry_webhook_event.py
databricks_registry_webhooks/entities/registry_webhook_status.py
databricks_registry_webhooks/entities/test_webhook_response.py
databricks_registry_webhooks/protos/__init__.py
databricks_registry_webhooks/protos/databricks_pb2.py
databricks_registry_webhooks/protos/webhooks_pb2.py
databricks_registry_webhooks/protos/scalapb/__init__.py
databricks_registry_webhooks/protos/scalapb/scalapb_pb2.py
databricks_registry_webhooks/utils/__init__.py
databricks_registry_webhooks/utils/databricks_utils.py
databricks_registry_webhooks/utils/logging_utils.py
databricks_registry_webhooks/utils/proto_json_utils.py
databricks_registry_webhooks/utils/rest_utils.py
databricks_registry_webhooks/utils/uri.py
databricks_registry_webhooks-0.1.2.dist-info/METADATA
databricks_registry_webhooks-0.1.2.dist-info/WHEEL
databricks_registry_webhooks-0.1.2.dist-info/top_level.txt
databricks_registry_webhooks-0.1.2.dist-info/RECORD
