Metadata-Version: 2.1
Name: databricks-registry-webhooks
Version: 0.1.2
Summary: Databricks MLflow Model Registry Webhooks Client
Home-page: https://docs.databricks.com/applications/mlflow/model-registry-webhooks.html
Author: Databricks
License: Apache License 2.0
Project-URL: Documentation, https://docs.databricks.com/applications/mlflow/model-registry-webhooks.html
Keywords: ml ai databricks mlops mlflow model registry webhooks triggers cicd events
Platform: UNKNOWN
Classifier: Intended Audience :: Developers
Classifier: Programming Language :: Python :: 3.7
Requires-Python: >=3.7
Requires-Dist: databricks-cli (>=0.8.7)
Requires-Dist: protobuf (>=3.7.0)
Requires-Dist: packaging
